sing_box_bin/__init__.py
sing_box_bin/py.typed
sing_box_bin/bin/sing-box-linux-amd64
sing_box_bin/bin/sing-box-windows-amd64.exe
sing_box_bin-1.12.18.dist-info/METADATA
sing_box_bin-1.12.18.dist-info/WHEEL
sing_box_bin-1.12.18.dist-info/entry_points.txt
sing_box_bin-1.12.18.dist-info/licenses/LICENSE
sing_box_bin-1.12.18.dist-info/RECORD
