Metadata-Version: 2.4
Name: sing-box-bin
Version: 1.12.18
Summary: python template package
Project-URL: Homepage, https://github.com/aittcuszz/sing-box-bin
Project-URL: Issues, https://github.com/atticuszeller/sing-box-bin/issues
Project-URL: documentation, https://atticuszeller.github.io/sing-box-bin/
Project-URL: Changelog, https://github.com/atticuszeller/sing-box-bin/blob/main/CHANGELOG.md
Author-email: "A.J.Zeller" <hello@atticux.me>
Maintainer-email: "A.J.Zeller" <hello@atticux.me>
License: MIT License
License-File: LICENSE
Classifier: License :: OSI Approved :: MIT License
Classifier: Programming Language :: Python
Classifier: Programming Language :: Python :: 3 :: Only
Classifier: Programming Language :: Python :: 3.11
Classifier: Programming Language :: Python :: 3.12
Classifier: Programming Language :: Python :: 3.13
Classifier: Programming Language :: Python :: 3.14
Requires-Python: >=3.10
